text_explainability/__init__.py
text_explainability/_version.py
text_explainability/decorators.py
text_explainability/model.py
text_explainability/utils.py
text_explainability/data/__init__.py
text_explainability/data/augmentation.py
text_explainability/data/embedding.py
text_explainability/data/sampling.py
text_explainability/data/weights.py
text_explainability/generation/__init__.py
text_explainability/generation/feature_selection.py
text_explainability/generation/return_types.py
text_explainability/generation/surrogate.py
text_explainability/generation/target_encoding.py
text_explainability/global_explanation/__init__.py
text_explainability/local_explanation/__init__.py
text_explainability/ui/__init__.py
text_explainability/ui/notebook.py
text_explainability-0.7.2.dist-info/LICENSE
text_explainability-0.7.2.dist-info/METADATA
text_explainability-0.7.2.dist-info/WHEEL
text_explainability-0.7.2.dist-info/top_level.txt
text_explainability-0.7.2.dist-info/RECORD
