Metadata-Version: 2.1
Name: text_explainability
Version: 0.7.2
Summary: Generic explainability architecture for text machine learning models
Home-page: https://text-explainability.readthedocs.io/
Author: Marcel Robeer
Author-email: m.j.robeer@uu.nl
License: GNU LGPL v3
Classifier: Development Status :: 3 - Alpha
Classifier: Programming Language :: Python
Classifier: License :: OSI Approved :: GNU Lesser General Public License v3 or later (LGPLv3+)
Classifier: Topic :: Scientific/Engineering :: Artificial Intelligence
Requires-Python: >=3.8
License-File: LICENSE
Requires-Dist: shap
Requires-Dist: instancelib (>=0.5.0)
Requires-Dist: genbase (>=0.3.6)
Requires-Dist: scikit-learn (>=1.0.2)
Requires-Dist: plotly (>=5.4.0)
Requires-Dist: sentence-transformers
Requires-Dist: scikit-learn-extra
Requires-Dist: imodels (>=1.2.7)
Provides-Extra: dev
Requires-Dist: genbase-test-helpers (>=0.1.1) ; extra == 'dev'
Provides-Extra: fast
Requires-Dist: fastcountvectorizer (>=0.1.0) ; extra == 'fast'
